ansitoimg/__init__.py
ansitoimg/__main__.py
ansitoimg/onedark.yml
ansitoimg/render.py
ansitoimg/resources/firacode
ansitoimg/resources/FiraCode-Bold.otf
ansitoimg/resources/FiraCode-BoldItalic.otf
ansitoimg/resources/FiraCode-Italic.otf
ansitoimg/resources/FiraCode-Regular.otf
ansitoimg/resources/twittercoloremoji
ansitoimg/resources/TwitterColorEmoji-SVGinOT.ttf
ansitoimg/resources/TwitterColorEmoji-SVGinOT30.ttf
ansitoimg/utils.py
ansitoimg-2024.2.dist-info/entry_points.txt
ansitoimg-2024.2.dist-info/LICENSE.md
ansitoimg-2024.2.dist-info/METADATA
ansitoimg-2024.2.dist-info/WHEEL
ansitoimg-2024.2.dist-info/RECORD
