Metadata-Version: 2.1
Name: ansitoimg
Version: 2024.2
Summary: Convert an ANSI string to an image. Great for adding terminal output into a readme.
Home-page: https://github.com/FHPythonUtils/AnsiToImg
License: MIT
Author: FredHappyface
Requires-Python: >=3.8,<4.0
Classifier: Development Status :: 5 - Production/Stable
Classifier: Intended Audience :: Developers
Classifier: Intended Audience :: Education
Classifier: License :: OSI Approved :: MIT License
Classifier: Natural Language :: English
Classifier: Operating System :: OS Independent
Classifier: Programming Language :: Python :: 3
Classifier: Programming Language :: Python :: 3.8
Classifier: Programming Language :: Python :: 3.9
Classifier: Programming Language :: Python :: 3.10
Classifier: Programming Language :: Python :: 3.11
Classifier: Programming Language :: Python :: 3.12
Classifier: Programming Language :: Python :: Implementation :: CPython
Classifier: Topic :: Software Development :: Libraries :: Python Modules
Classifier: Topic :: Utilities
Requires-Dist: PyYAML (>=6.0.1,<7)
Requires-Dist: install-playwright (>=0.0.1,<2)
Requires-Dist: playwright (>=1.42.0,<2)
Requires-Dist: rich (>=13.7.1,<14)
Project-URL: Documentation, https://github.com/FHPythonUtils/AnsiToImg/blob/master/README.md
Project-URL: Repository, https://github.com/FHPythonUtils/AnsiToImg
